madzpy/__init__.py
madzpy/madz.py
madzpy/utils.py
madzpy-0.7.dist-info/LICENSE
madzpy-0.7.dist-info/METADATA
madzpy-0.7.dist-info/WHEEL
madzpy-0.7.dist-info/top_level.txt
madzpy-0.7.dist-info/RECORD
