Metadata-Version: 2.1
Name: madzpy
Version: 0.7
Summary: Madzcoin RPC Client
Home-page: https://github.com/MadzCoin/madz-py/
Download-URL: https://github.com/MadzCoin/madz-py/archive/refs/heads/main.zip
Author: Bastel Pichi
Author-email: madzcoin@pichisdns.com
License: MIT
Keywords: Madzcoin,Crypto,RPC
License-File: LICENSE
Requires-Dist: web3
Requires-Dist: eth-account
Requires-Dist: requests
